setup.cfg
setup.py
cache_tier/__init__.py
cache_tier/cache_client.py
cache_tier.egg-info/PKG-INFO
cache_tier.egg-info/SOURCES.txt
cache_tier.egg-info/dependency_links.txt
cache_tier.egg-info/requires.txt
cache_tier.egg-info/top_level.txt