Metadata-Version: 1.1
Name: cache-tier
Version: 1.0.4
Summary: Imagine you have a set of static files you want to serve to the world. Cache-tier allows you to quickly spin up a Linux web server in a location with cheap, plentiful bandwidth and serve those files to your users.
Home-page: https://github.com/mikeckennedy/cache-tier
Author: Michael Kennedy - @mkennedy
Author-email: mikeckennedy+pypi@gmail.com
License: MIT License
Download-URL: https://github.com/mikeckennedy/cache-tier/tarball/1.0.4
Keywords: caching,cache-tier,cache,tier
Platform: UNKNOWN
